LICENSE.txt
MANIFEST.in
README.md
setup.cfg
setup.py
anyone/__init__.py
anyone/anyone.py
anyone/data.json
anyone.egg-info/PKG-INFO
anyone.egg-info/SOURCES.txt
anyone.egg-info/dependency_links.txt
anyone.egg-info/entry_points.txt
anyone.egg-info/not-zip-safe
anyone.egg-info/top_level.txt
tests/__init__.py
tests/__init__.pyc
tests/test_anyone.py
tests/__pycache__/__init__.cpython-36.pyc
tests/__pycache__/test_anyone.cpython-27-PYTEST.pyc
tests/__pycache__/test_anyone.cpython-36-PYTEST.pyc