Metadata-Version: 1.1
Name: anyone
Version: 0.1.14
Summary: anyone lived in a pretty how town - the poem
Home-page: https://github.com/herereadthis/anyone
Author: herereadthis
Author-email: herereadthis@gmail.com
License: MIT
Keywords: sample development poem
Platform: UNKNOWN
Classifier: Development Status :: 3 - Alpha
Classifier: Intended Audience :: Developers
Classifier: License :: OSI Approved :: MIT License
Classifier: Programming Language :: Python :: 3
